{
 "systemProperties": {
  "placementToolName": "SIGN_PLACEMENT_TOOL",
  "signalTypeName": "rasignal",
  "canLink": true,
  "defaultHeight": 0
 },
 "seProperties": [
  {
   "name": "ratype",
   "enumClass": "RA",
   "defaultState": "RA10",
   "changeableStage": "GUISTAGE"
  },
  {
   "name": "ralight",
   "defaultState": true,
   "changeableStage": "APISTAGE",
   "autoname": true,
   "dependencies": "check(RA.RA11A)"
  },
  {
   "name": "ralightsignal",
   "enumClass": "RALight",
   "defaultState": "OFF",
   "changeableStage": "APISTAGE_NONE_CONFIG",
   "autoname": true,
   "dependencies": "check(RA.RA6_9)"
  }
 ]
}